png2jpg/__init__.py
png2jpg/__main__.py
png2jpg/converter.py
png2jpg-0.1.0.dist-info/licenses/LICENSE
png2jpg-0.1.0.dist-info/METADATA
png2jpg-0.1.0.dist-info/WHEEL
png2jpg-0.1.0.dist-info/entry_points.txt
png2jpg-0.1.0.dist-info/top_level.txt
png2jpg-0.1.0.dist-info/RECORD
