Metadata-Version: 2.4
Name: png2jpg
Version: 0.1.0
Summary: A Python package to convert PNG images to JPG format while maintaining directory structure
Author-email: Tuan Anh Bui <bta1489@gmail.com>
Maintainer-email: Tuan Anh Bui <bta1489@gmail.com>
License: MIT
Project-URL: Homepage, https://github.com/tuananhbui89/png2jpg
Project-URL: Repository, https://github.com/tuananhbui89/png2jpg.git
Project-URL: Documentation, https://github.com/tuananhbui89/png2jpg#readme
Project-URL: Bug Tracker, https://github.com/tuananhbui89/png2jpg/issues
Keywords: png,jpg,jpeg,image,conversion,converter
Classifier: Development Status :: 4 - Beta
Classifier: Intended Audience :: Developers
Classifier: Intended Audience :: End Users/Desktop
Classifier: License :: OSI Approved :: MIT License
Classifier: Operating System :: OS Independent
Classifier: Programming Language :: Python :: 3
Classifier: Programming Language :: Python :: 3.8
Classifier: Programming Language :: Python :: 3.9
Classifier: Programming Language :: Python :: 3.10
Classifier: Programming Language :: Python :: 3.11
Classifier: Programming Language :: Python :: 3.12
Classifier: Topic :: Multimedia :: Graphics :: Graphics Conversion
Classifier: Topic :: Software Development :: Libraries :: Python Modules
Classifier: Topic :: Utilities
Requires-Python: >=3.8
License-File: LICENSE
Requires-Dist: Pillow>=8.0.0
Provides-Extra: dev
Requires-Dist: pytest>=6.0; extra == "dev"
Requires-Dist: pytest-cov; extra == "dev"
Requires-Dist: black; extra == "dev"
Requires-Dist: flake8; extra == "dev"
Requires-Dist: mypy; extra == "dev"
Dynamic: license-file
